django_amenities/__init__.py
django_amenities/admin.py
django_amenities/apps.py
django_amenities/models.py
django_amenities/updater.py
django_amenities/utils.py
django_amenities/management/__init__.py
django_amenities/management/commands/__init__.py
django_amenities/management/commands/update_amenities.py
django_amenities/migrations/0001_initial.py
django_amenities/migrations/0002_amenity_topics.py
django_amenities/migrations/0003_auto_20200724_1529.py
django_amenities/migrations/__init__.py
django_amenities-0.0.3.dist-info/LICENSE
django_amenities-0.0.3.dist-info/METADATA
django_amenities-0.0.3.dist-info/WHEEL
django_amenities-0.0.3.dist-info/top_level.txt
django_amenities-0.0.3.dist-info/RECORD
